odoo/addons/website_sale_decimal/README.md
odoo/addons/website_sale_decimal/__init__.py
odoo/addons/website_sale_decimal/__manifest__.py
odoo/addons/website_sale_decimal/static/src/js/website_sale.js
odoo/addons/website_sale_decimal/views/assets.xml
odoo12_addon_website_sale_decimal-12.0.0.1.0.dist-info/METADATA
odoo12_addon_website_sale_decimal-12.0.0.1.0.dist-info/WHEEL
odoo12_addon_website_sale_decimal-12.0.0.1.0.dist-info/top_level.txt
odoo12_addon_website_sale_decimal-12.0.0.1.0.dist-info/RECORD
